ariadne_token_auth/__init__.py
ariadne_token_auth/admin.py
ariadne_token_auth/api/resolvers.py
ariadne_token_auth/apps.py
ariadne_token_auth/backends.py
ariadne_token_auth/decorators.py
ariadne_token_auth/exceptions.py
ariadne_token_auth/middleware.py
ariadne_token_auth/migrations/0001_initial.py
ariadne_token_auth/migrations/__init__.py
ariadne_token_auth/models.py
ariadne_token_auth/utils.py
ariadne_token_auth-0.1.2.dist-info/LICENSE
ariadne_token_auth-0.1.2.dist-info/WHEEL
ariadne_token_auth-0.1.2.dist-info/METADATA
ariadne_token_auth-0.1.2.dist-info/RECORD
