Metadata-Version: 2.1
Name: ariadne-token-auth
Version: 0.1.2
Summary: A django app to implement token based authentication in Ariadne GraphQL
Home-page: https://github.com/IgnisDa/ariadne-token-auth
License: Apache-2.0
Author: IgnisDa
Author-email: ignisda2002@gmail.com
Requires-Python: >=3.6.1,<4.0.0
Classifier: License :: OSI Approved :: Apache Software License
Classifier: Operating System :: OS Independent
Classifier: Programming Language :: Python :: 3
Classifier: Programming Language :: Python :: 3.6
Classifier: Programming Language :: Python :: 3.7
Classifier: Programming Language :: Python :: 3.8
Classifier: Programming Language :: Python :: 3.9
Requires-Dist: Django (>=3.0,<4.0)
Requires-Dist: ariadne (>=0.12.0)
Project-URL: Repository, https://github.com/IgnisDa/ariadne-token-auth
